{"2023-10-04 21:02:06.241940": {"username": "Leshiy", "message": "qqq"}, "2023-10-04 21:02:15.874068": {"username": "Leshiy", "message": "www"}, "2023-10-08 18:57:06.056536": {"username": "Leshiy", "message": "qqq"}, "2023-10-08 20:08:14.076484": {"username": "Leshiy", "message": "yyy"}, "2023-10-10 00:52:37.650695": {"username": "Leshiy", "message": "fffffff"}, "2023-10-10 00:58:07.580776": {"username": "Leshiy", "message": "hhhh"}, "2023-10-10 01:25:58.857949": {"username": "Leshiy", "message": "jjjjj"}, "2023-10-10 01:29:43.126618": {"username": "Leshiy", "message": "kkkk"}, "2023-10-10 23:16:57.117347": {"username": "Leshiy", "message": "ttt"}, "2023-10-10 23:46:43.426010": {"username": "Leshiy", "message": "lll"}, "2023-10-11 00:59:21.202087": {"username": "Leshiy", "message": "fgfgfg"}, "2023-10-11 01:01:53.728446": {"username": "Leshiy", "message": "jhkhjk"}, "2023-10-11 01:04:58.747233": {"username": "Leshiy", "message": "fdgdfg"}, "2023-10-11 01:18:06.558101": {"username": "Leshiy", "message": "rtyui"}}